webagt.py
webagt-0.2.3.dist-info/METADATA
webagt-0.2.3.dist-info/entry_points.txt
webagt-0.2.3.dist-info/WHEEL
webagt-0.2.3.dist-info/RECORD
