Metadata-Version: 2.1
Name: webagt
Version: 0.2.3
Summary: a web agent
Home-page: https://ragt.ag/code/projects/webagt
License: BSD-2-Clause
Author: Angelo Gladding
Author-email: angelo@ragt.ag
Requires-Python: >=3.10,<3.11
Classifier: License :: OSI Approved :: BSD License
Classifier: Programming Language :: Python :: 3
Classifier: Programming Language :: Python :: 3.10
Requires-Dist: certifi (>=2022.12.7,<2023.0.0)
Requires-Dist: cssselect (>=1.2.0,<2.0.0)
Requires-Dist: easyuri (>=0.0.12)
Requires-Dist: httpagentparser (>=1.9.5,<2.0.0)
Requires-Dist: lxml (>=4.9.2,<5.0.0)
Requires-Dist: microformats (>=0.5.0,<0.6.0)
Requires-Dist: mimeparse (>=0.1.3,<0.2.0)
Requires-Dist: pendulum (>=2.1.2,<3.0.0)
Requires-Dist: pyscreenshot (>=3.0,<4.0)
Requires-Dist: pyvirtualdisplay (>=3.0,<4.0)
Requires-Dist: requests[socks] (>=2.28.2,<3.0.0)
Requires-Dist: selenium (>=4.8.0,<5.0.0)
Requires-Dist: sqlyte (>=0.0.50)
Requires-Dist: txtint (>=0.0.68)
Requires-Dist: webdriver-manager (>=3.8.5,<4.0.0)
